oratio/__init__.py
oratio-0.2.0.dist-info/licenses/LICENSE
oratio-0.2.0.dist-info/METADATA
oratio-0.2.0.dist-info/WHEEL
oratio-0.2.0.dist-info/entry_points.txt
oratio-0.2.0.dist-info/top_level.txt
oratio-0.2.0.dist-info/RECORD
