Metadata-Version: 2.4
Name: oratio
Version: 0.2.0
Summary: ORATIO - Natural language programming in Italian and English
Author-email: Manuel Lazzaro <manuel@oratio.dev>
License: MIT
Project-URL: Homepage, https://oratio.dev
Project-URL: Documentation, https://oratio.dev/docs
Project-URL: Repository, https://github.com/manuellazzaro/oratio
Project-URL: Issues, https://github.com/manuellazzaro/oratio/issues
Keywords: natural-language,programming,ai,llm,italian,oratio,eloquence
Classifier: Development Status :: 2 - Pre-Alpha
Classifier: Intended Audience :: Developers
Classifier: License :: OSI Approved :: MIT License
Classifier: Programming Language :: Python :: 3.11
Classifier: Programming Language :: Python :: 3.12
Classifier: Topic :: Software Development :: Compilers
Classifier: Topic :: Software Development :: Interpreters
Requires-Python: >=3.11
License-File: LICENSE
Requires-Dist: openai>=1.3.0
Requires-Dist: anthropic>=0.7.0
Requires-Dist: pandas>=2.1.0
Requires-Dist: numpy>=1.24.0
Requires-Dist: matplotlib>=3.8.0
Requires-Dist: chromadb>=0.4.18
Requires-Dist: sentence-transformers>=2.2.0
Requires-Dist: pydantic>=2.5.0
Requires-Dist: rich>=13.7.0
Requires-Dist: typer>=0.9.0
Provides-Extra: dev
Requires-Dist: pytest>=7.4.0; extra == "dev"
Requires-Dist: pytest-asyncio>=0.21.0; extra == "dev"
Requires-Dist: black>=23.11.0; extra == "dev"
Requires-Dist: ruff>=0.1.6; extra == "dev"
Requires-Dist: mypy>=1.7.0; extra == "dev"
Provides-Extra: local-llm
Requires-Dist: torch>=2.1.0; extra == "local-llm"
Requires-Dist: transformers>=4.35.0; extra == "local-llm"
Requires-Dist: peft>=0.7.0; extra == "local-llm"
Requires-Dist: bitsandbytes>=0.41.0; extra == "local-llm"
Requires-Dist: accelerate>=0.25.0; extra == "local-llm"
Dynamic: license-file
